rui_utils/__init__.py
rui_utils/gpu.py
rui_utils/knn.py
rui_utils/ray/alloc.py
rui_utils/ray/release.py
rui_utils/sc.py
rui_utils/torch/__init__.py
rui_utils/torch/layers.py
rui_utils/torch/lightning.py
rui_utils/torch/trainer.py
rui_utils/utils.py
rui_utils-0.1.3.dist-info/METADATA
rui_utils-0.1.3.dist-info/WHEEL
rui_utils-0.1.3.dist-info/licenses/LICENSE
rui_utils-0.1.3.dist-info/RECORD
