Metadata-Version: 2.4
Name: rui_utils
Version: 0.1.3
Summary: Utils functions
License: MIT
License-File: LICENSE
Keywords: ADDME
Author: Chen-Rui Xia
Author-email: xiachenrui@mail.cbi.pku.edu.cn
Requires-Python: >=3.10
Classifier: Intended Audience :: Science/Research
Classifier: License :: OSI Approved :: MIT License
Classifier: Natural Language :: English
Classifier: Operating System :: MacOS :: MacOS X
Classifier: Operating System :: POSIX :: Linux
Classifier: Programming Language :: Python :: 3
Classifier: Programming Language :: Python :: 3.10
Classifier: Programming Language :: Python :: 3.11
Classifier: Programming Language :: Python :: 3.12
Classifier: Programming Language :: Python :: 3.13
Classifier: Programming Language :: Python :: 3.14
Classifier: Topic :: Scientific/Engineering :: Bio-Informatics
Provides-Extra: rapids
Provides-Extra: test
Provides-Extra: torch
Requires-Dist: annoy
Requires-Dist: cudf-cu12 (==25.8.*) ; extra == "rapids"
Requires-Dist: cugraph-cu12 (==25.8.*) ; extra == "rapids"
Requires-Dist: cuml-cu12 (==25.8.*) ; extra == "rapids"
Requires-Dist: einops ; extra == "torch"
Requires-Dist: faiss-cpu
Requires-Dist: ipython
Requires-Dist: loguru
Requires-Dist: omegaconf
Requires-Dist: pynvml
Requires-Dist: pytest ; extra == "test"
Requires-Dist: pytest-cov ; extra == "test"
Requires-Dist: pytest-order ; extra == "test"
Requires-Dist: pytest-sugar ; extra == "test"
Requires-Dist: pytest-xdist ; extra == "test"
Requires-Dist: pytorch-lightning (>=2.1) ; extra == "torch"
Requires-Dist: pyyaml
Requires-Dist: rapids_singlecell ; extra == "rapids"
Requires-Dist: scanpy
Requires-Dist: tensorboard ; extra == "torch"
Requires-Dist: torch (>=2.0) ; extra == "torch"
Requires-Dist: torchaudio ; extra == "torch"
Requires-Dist: torchvision ; extra == "torch"
Project-URL: Documentation, https://github.com/xiachenrui/rui_utils
Project-URL: Homepage, https://github.com/xiachenrui/rui_utils
Project-URL: Repository, https://github.com/xiachenrui/rui_utils
